datatype_redis/__init__.py
datatype_redis/client.py
datatype_redis/redisclient.py
datatype_redis-0.1.dist-info/LICENSE
datatype_redis-0.1.dist-info/METADATA
datatype_redis-0.1.dist-info/WHEEL
datatype_redis-0.1.dist-info/top_level.txt
datatype_redis-0.1.dist-info/RECORD
