Metadata-Version: 2.1
Name: datatype-redis
Version: 0.1
Summary: Add redis to all python3 builtin datatypes to use in microservice ecosystems.
Home-page: https://github.com/Heiss/py-datatype-redis
Author: Peter Heiss
Author-email: peter.heiss@uni-muenster.de
Maintainer: Peter Heiss
Maintainer-email: peter.heiss@uni-muenster.de
License: MIT
Keywords: Redis,key-value store,Datatype,Datastructure
Platform: UNKNOWN
Classifier: Development Status :: 2 - Pre-Alpha
Classifier: Environment :: Console
Classifier: Intended Audience :: Developers
Classifier: License :: OSI Approved :: MIT License
Classifier: Operating System :: OS Independent
Classifier: Programming Language :: Python
Classifier: Programming Language :: Python :: 3
Classifier: Programming Language :: Python :: 3.6
Classifier: Programming Language :: Python :: 3.7
Classifier: Programming Language :: Python :: 3.8
Classifier: Programming Language :: Python :: Implementation :: CPython
Requires-Python: >=3.6
Requires-Dist: pylru (==1.2.0)
Requires-Dist: redis-py-cluster (==2.0.0)
Requires-Dist: redis (==3.0.1)
